configuration/__init__.py
configuration/configuration.py
configuration/configuration_builder.py
configuration/configuration_source.py
configuration/section.py
configuration/sources/__init__.py
configuration/sources/json_config_source.py
configuration/sources/memory_config_source.py
multi_config-0.2.0.dist-info/LICENSE
multi_config-0.2.0.dist-info/METADATA
multi_config-0.2.0.dist-info/WHEEL
multi_config-0.2.0.dist-info/top_level.txt
multi_config-0.2.0.dist-info/RECORD
