Metadata-Version: 2.1
Name: multi-config
Version: 0.2.0
Summary: Python configuration from multiple sources
Home-page: https://github.com/EvanAranda/multi-config
Author: Evan Aranda
Author-email: UNKNOWN
License: MIT
Platform: UNKNOWN
